{
 "sections": [
  {
   "id": "94a5ace7-2f9d-2913-e9c5-e8245d16a7da",
   "title": "Welcome",
   "files": [
    {
     "path": "#tabs",
     "action": "close"
    }
   ],
   "layout": "1-panel",
   "path": [],
   "type": "html",
   "content-file": ".guides/content/Welcome-94a5.html",
   "chapter": false,
   "reset": [],
   "teacherOnly": false,
   "closeTerminalSession": true,
   "learningObjectives": ""
  },
  {
   "id": "25781cbf-d586-7199-cdf3-f42e2e6a5191",
   "title": "What is Javascript?",
   "files": [
    {
     "path": "#tabs",
     "action": "close"
    }
   ],
   "layout": "",
   "path": [],
   "type": "html",
   "content-file": ".guides/content/What-is-Javascript--2578.html",
   "chapter": false,
   "reset": [],
   "teacherOnly": false,
   "closeTerminalSession": true,
   "learningObjectives": ""
  },
  {
   "id": "75ca7f69-9ce1-e132-f960-0b65454624b5",
   "title": "The Javascript Console",
   "files": [
    {
     "path": "#tabs",
     "action": "close"
    },
    {
     "path": "#preview: /.guides/p/#consoleOnly",
     "panel": 0,
     "action": "open"
    }
   ],
   "layout": "2-panels",
   "path": [],
   "type": "html",
   "content-file": ".guides/content/The-Javascript-Console-75ca.html",
   "chapter": false,
   "reset": [],
   "teacherOnly": false,
   "closeTerminalSession": true,
   "learningObjectives": ""
  },
  {
   "id": "cb47b725-3dfd-874d-11e3-83e65c0ff093",
   "title": "Running Javascript from a File",
   "files": [
    {
     "path": "#tabs",
     "action": "close"
    }
   ],
   "layout": "1-panel",
   "path": [],
   "type": "html",
   "content-file": ".guides/content/Running-Javascript-from-a-File-cb47.html",
   "chapter": false,
   "reset": [],
   "teacherOnly": false,
   "closeTerminalSession": true,
   "learningObjectives": ""
  },
  {
   "id": "1095aba6-2fe7-e244-5e8a-0eab9c2c3749",
   "title": "Inline Scripts",
   "files": [
    {
     "path": "01-intro-to-javascript/javascript-practice.html",
     "panel": 0,
     "action": "open"
    },
    {
     "path": "#preview: .guides/p/#preview=/01-intro-to-javascript/javascript-practice.html&consoleSize=115px",
     "panel": 1,
     "action": "open"
    }
   ],
   "layout": "3-cell-tree",
   "path": [],
   "type": "html",
   "content-file": ".guides/content/Inline-Scripts-1095.html",
   "chapter": false,
   "reset": [],
   "teacherOnly": false,
   "closeTerminalSession": true,
   "learningObjectives": ""
  },
  {
   "id": "d7e82ebc-65f5-a6fd-f15e-6bf44a59bed7",
   "title": "External Scripts",
   "files": [
    {
     "path": "01-intro-to-javascript/javascript-practice.html",
     "panel": 0,
     "action": "open"
    },
    {
     "path": "#preview: .guides/p/#preview=/01-intro-to-javascript/javascript-practice.html&consoleSize=115px",
     "panel": 1,
     "action": "open"
    }
   ],
   "path": [],
   "type": "html",
   "content-file": ".guides/content/External-Scripts-d7e8.html",
   "chapter": false,
   "reset": [],
   "teacherOnly": false,
   "closeTerminalSession": true,
   "learningObjectives": ""
  },
  {
   "id": "299ef57d-6592-558b-c8e0-60af9fea822e",
   "title": "Semicolons",
   "files": [
    {
     "path": "#tabs",
     "action": "close"
    }
   ],
   "layout": "1-panel",
   "path": [],
   "type": "html",
   "content-file": ".guides/content/Semicolons-299e.html",
   "chapter": false,
   "reset": [],
   "teacherOnly": false,
   "closeTerminalSession": true,
   "learningObjectives": ""
  },
  {
   "id": "38e1eb8e-0cd3-0d36-970a-96b365ee00a7",
   "title": "Understanding Error Messages",
   "files": [
    {
     "path": "01-intro-to-javascript/practice.js",
     "panel": 0,
     "action": "open"
    },
    {
     "path": "#preview: .guides/p/#preview=/01-intro-to-javascript/javascript-practice.html&consoleSize=150px",
     "panel": 1,
     "action": "open"
    }
   ],
   "layout": "3-cell-tree",
   "path": [],
   "type": "html",
   "content-file": ".guides/content/Understanding-Error-Messages-38e1.html",
   "chapter": false,
   "reset": [],
   "teacherOnly": false,
   "closeTerminalSession": true,
   "learningObjectives": ""
  },
  {
   "id": "cee27749-5970-c322-ce4a-c31e69795ff1",
   "title": "Comments",
   "files": [
    {
     "path": "#tabs",
     "action": "close"
    }
   ],
   "layout": "1-panel",
   "path": [],
   "type": "html",
   "content-file": ".guides/content/Comments-cee2.html",
   "chapter": false,
   "reset": [],
   "teacherOnly": false,
   "closeTerminalSession": true,
   "learningObjectives": ""
  },
  {
   "id": "0130e4fc-236c-d1f2-eca2-0a28af3c111c",
   "title": "Multi-line Comments",
   "files": [],
   "path": [],
   "type": "html",
   "content-file": ".guides/content/Multi-line-Comments-0130.html",
   "chapter": false,
   "reset": [],
   "teacherOnly": false,
   "closeTerminalSession": true,
   "learningObjectives": ""
  },
  {
   "id": "5269cc76-6f23-88d3-5388-b05f12364dac",
   "title": "Expressions",
   "files": [],
   "path": [],
   "type": "html",
   "content-file": ".guides/content/Expressions-5269.html",
   "chapter": false,
   "reset": [],
   "teacherOnly": false,
   "closeTerminalSession": true,
   "learningObjectives": ""
  },
  {
   "id": "c31c95b9-8c58-90a4-b18a-43bef31848e8",
   "title": "Math Expressions",
   "files": [
    {
     "path": "#tabs",
     "action": "close"
    },
    {
     "path": "#preview: .guides/p/#consoleOnly",
     "panel": 0,
     "action": "open"
    }
   ],
   "layout": "2-panels",
   "path": [],
   "type": "html",
   "content-file": ".guides/content/Math-Expressions-c31c.html",
   "chapter": false,
   "reset": [],
   "teacherOnly": false,
   "closeTerminalSession": true,
   "learningObjectives": ""
  },
  {
   "id": "85bd33d1-3dad-0a14-2c8a-85149d47ce9a",
   "title": "String Expressions",
   "files": [],
   "path": [],
   "type": "html",
   "content-file": ".guides/content/String-Expressions-85bd.html",
   "chapter": false,
   "reset": [],
   "teacherOnly": false,
   "closeTerminalSession": true,
   "learningObjectives": ""
  },
  {
   "id": "6631822f-e1d4-8e9a-dbc8-917294b51ca0",
   "title": "Variables",
   "files": [],
   "path": [],
   "type": "html",
   "content-file": ".guides/content/Variables-6631.html",
   "chapter": false,
   "reset": [],
   "teacherOnly": false,
   "closeTerminalSession": true,
   "learningObjectives": ""
  },
  {
   "id": "101e1ee1-063c-2af0-07de-f51610d99527",
   "title": "Declaring and Re-assigning Variables",
   "files": [],
   "path": [],
   "type": "html",
   "content-file": ".guides/content/Declaring-and-Re-assigning-Variables-101e.html",
   "chapter": false,
   "reset": [],
   "teacherOnly": false,
   "closeTerminalSession": true,
   "learningObjectives": ""
  },
  {
   "id": "cfeebf3e-22be-6ecf-79f6-ebeb7b901917",
   "title": "Incrementing and Decrementing Numbers",
   "files": [],
   "path": [],
   "type": "html",
   "content-file": ".guides/content/Incrementing-and-Decrementing-Numbers-cfee.html",
   "chapter": false,
   "reset": [],
   "teacherOnly": false,
   "closeTerminalSession": true,
   "learningObjectives": ""
  },
  {
   "id": "9d106a77-628a-cc23-b678-e433d0fcab49",
   "title": "Naming",
   "files": [],
   "path": [],
   "type": "html",
   "content-file": ".guides/content/Naming-9d10.html",
   "chapter": false,
   "reset": [],
   "teacherOnly": false,
   "closeTerminalSession": true,
   "learningObjectives": ""
  },
  {
   "id": "d77e9669-02d3-c85b-15b4-dee029719eea",
   "title": "alert() and prompt()",
   "files": [],
   "path": [],
   "type": "html",
   "content-file": ".guides/content/alert---and-prompt---d77e.html",
   "chapter": false,
   "reset": [],
   "teacherOnly": false,
   "closeTerminalSession": true,
   "learningObjectives": ""
  },
  {
   "id": "63e459b2-6ffb-0bcf-0089-53a603dbda6b",
   "title": "Code Challenge: Turtle Squares",
   "files": [
    {
     "path": "#tabs",
     "action": "close"
    },
    {
     "path": "02-expressions-and-variables/turtle-squares.js",
     "panel": 0,
     "action": "open"
    }
   ],
   "layout": "2-panels",
   "path": [],
   "type": "html",
   "content-file": ".guides/content/Code-Challenge--Turtle-Squares-63e4.html",
   "chapter": false,
   "reset": [],
   "teacherOnly": false,
   "closeTerminalSession": true,
   "learningObjectives": ""
  },
  {
   "id": "31d24dc8-64ff-65c6-284c-15d7465949b4",
   "title": "Working with Strings",
   "files": [],
   "path": [],
   "type": "html",
   "content-file": ".guides/content/Working-with-Strings-31d2.html",
   "chapter": false,
   "reset": [],
   "teacherOnly": false,
   "closeTerminalSession": true,
   "learningObjectives": ""
  },
  {
   "id": "6b4baca4-8795-f35c-74ac-20398b7b941f",
   "title": "String Methods",
   "files": [],
   "path": [],
   "type": "html",
   "content-file": ".guides/content/String-Methods-6b4b.html",
   "chapter": false,
   "reset": [],
   "teacherOnly": false,
   "closeTerminalSession": true,
   "learningObjectives": ""
  },
  {
   "id": "3081a701-dc28-b64f-0079-4c79ea82572c",
   "title": "Strings vs. Numbers",
   "files": [],
   "path": [],
   "type": "html",
   "content-file": ".guides/content/Strings-vs--Numbers-3081.html",
   "chapter": false,
   "reset": [],
   "teacherOnly": false,
   "closeTerminalSession": true,
   "learningObjectives": ""
  },
  {
   "id": "fce78673-a2ee-6135-a03d-dc35e058face",
   "title": "Converting strings to numbers",
   "files": [],
   "path": [],
   "type": "html",
   "content-file": ".guides/content/Converting-strings-to-numbers-fce7.html",
   "chapter": false,
   "reset": [],
   "teacherOnly": false,
   "closeTerminalSession": true,
   "learningObjectives": ""
  },
  {
   "id": "1e69dc2f-439c-fd1c-7cfb-b571ec6f235e",
   "title": "Code Challenge - Age Predictor",
   "files": [
    {
     "path": "#tabs",
     "action": "close"
    },
    {
     "path": "03-working-with-strings/age-predictor.js",
     "panel": 0,
     "action": "open"
    }
   ],
   "layout": "3-cell",
   "path": [],
   "type": "html",
   "content-file": ".guides/content/Code-Challenge---Age-Predictor-1e69.html",
   "chapter": false,
   "reset": [],
   "teacherOnly": false,
   "closeTerminalSession": true,
   "learningObjectives": ""
  },
  {
   "id": "08de67c0-1ee3-f448-2297-b8149ff231c6",
   "title": "Functions intro",
   "files": [
    {
     "path": "#tabs",
     "action": "close"
    }
   ],
   "layout": "1-panel",
   "path": [],
   "type": "html",
   "content-file": ".guides/content/Functions-intro-08de.html",
   "chapter": false,
   "reset": [],
   "teacherOnly": false,
   "closeTerminalSession": true,
   "learningObjectives": ""
  },
  {
   "id": "031427ee-c789-1b5e-402d-8833bc3d1c8f",
   "title": "Defining Functions",
   "files": [
    {
     "path": "#tabs",
     "action": "close"
    },
    {
     "path": "04-functions/pbj-function.js",
     "panel": 0,
     "action": "open"
    },
    {
     "path": "#preview: /.guides/p/#preview=/04-functions/pbj-function.html&consoleSize=90%25",
     "panel": 1,
     "action": "open"
    }
   ],
   "layout": "3-cell",
   "path": [],
   "type": "html",
   "content-file": ".guides/content/Defining-Functions-0314.html",
   "chapter": false,
   "reset": [],
   "teacherOnly": false,
   "closeTerminalSession": true,
   "learningObjectives": ""
  },
  {
   "id": "67000ce0-2444-d57b-63c8-3714f80096ab",
   "title": "Calling Functions",
   "files": [],
   "path": [],
   "type": "html",
   "content-file": ".guides/content/Calling-Functions-6700.html",
   "chapter": false,
   "reset": [],
   "teacherOnly": false,
   "closeTerminalSession": true,
   "learningObjectives": ""
  },
  {
   "id": "7b8a9f85-7984-8f29-e99f-7ff5e71c613d",
   "title": "Function Parameters",
   "files": [
    {
     "path": "#tabs",
     "action": "close"
    }
   ],
   "layout": "1-panel",
   "path": [],
   "type": "html",
   "content-file": ".guides/content/Function-Parameters-7b8a.html",
   "chapter": false,
   "reset": [],
   "teacherOnly": false,
   "closeTerminalSession": true,
   "learningObjectives": ""
  },
  {
   "id": "71947624-296f-75ae-d7f6-a6b397810206",
   "title": "Using Parameters",
   "files": [
    {
     "path": "#tabs",
     "action": "close"
    },
    {
     "path": "04-functions/pbj-function.js",
     "panel": 0,
     "action": "open"
    },
    {
     "path": "#preview: .guides/p/#preview=/04-functions/pbj-function.html&consoleSize=90%25",
     "panel": 1,
     "action": "open"
    }
   ],
   "layout": "3-cell",
   "path": [],
   "type": "html",
   "content-file": ".guides/content/Using-Parameters-7194.html",
   "chapter": false,
   "reset": [],
   "teacherOnly": false,
   "closeTerminalSession": true,
   "learningObjectives": ""
  },
  {
   "id": "3222709a-179f-44de-1799-3ace5bd27658",
   "title": "What happened here?",
   "files": [],
   "path": [],
   "type": "html",
   "content-file": ".guides/content/What-happened-here--3222.html",
   "chapter": false,
   "reset": [],
   "teacherOnly": false,
   "closeTerminalSession": true,
   "learningObjectives": ""
  },
  {
   "id": "77b5c9d4-3746-6265-874b-0b98774f0800",
   "title": "Adding more parameters",
   "files": [],
   "path": [],
   "type": "html",
   "content-file": ".guides/content/Adding-more-parameters-77b5.html",
   "chapter": false,
   "reset": [],
   "teacherOnly": false,
   "closeTerminalSession": true,
   "learningObjectives": ""
  },
  {
   "id": "87b6cc4b-f132-98fb-200d-fb5206960fb3",
   "title": "Code Challenge: Turtle House Neighborhood",
   "files": [
    {
     "path": "#tabs",
     "action": "close"
    },
    {
     "path": "04-functions/turtle-houses.js",
     "panel": 0,
     "action": "open"
    }
   ],
   "layout": "2-panels",
   "path": [],
   "type": "html",
   "content-file": ".guides/content/Code-Challenge--Turtle-House-Neighborhood-87b6.html",
   "chapter": false,
   "reset": [],
   "teacherOnly": false,
   "closeTerminalSession": true,
   "learningObjectives": ""
  },
  {
   "id": "efd1edcd-d534-3497-5c4e-8ba3bfbde6f6",
   "title": "Drawing graphics with p5.js",
   "files": [
    {
     "path": "#tabs",
     "action": "close"
    }
   ],
   "layout": "1-panel",
   "path": [],
   "type": "html",
   "content-file": ".guides/content/Drawing-graphics-with-p5-js-efd1.html",
   "chapter": false,
   "reset": [],
   "teacherOnly": false,
   "closeTerminalSession": true,
   "learningObjectives": ""
  },
  {
   "id": "dde74c31-2e76-a522-b72b-9fbe2c6bac83",
   "title": "Coordinate Systems",
   "files": [],
   "path": [],
   "type": "html",
   "content-file": ".guides/content/Coordinate-Systems-dde7.html",
   "chapter": false,
   "reset": [],
   "teacherOnly": false,
   "closeTerminalSession": true,
   "learningObjectives": ""
  },
  {
   "id": "5f4e4d28-fd80-7218-9f1f-cc84feacaf7e",
   "title": "Getting started with p5.js",
   "files": [
    {
     "path": "#tabs",
     "action": "close"
    },
    {
     "path": "05-drawing/drawing.html",
     "panel": 0,
     "action": "open"
    },
    {
     "path": "05-drawing/drawing.js",
     "panel": 1,
     "action": "open"
    }
   ],
   "layout": "3-cell",
   "path": [],
   "type": "html",
   "content-file": ".guides/content/Getting-started-with-p5-js-5f4e.html",
   "chapter": false,
   "reset": [],
   "teacherOnly": false,
   "closeTerminalSession": true,
   "learningObjectives": ""
  },
  {
   "id": "0f892c31-fa53-90a6-79f0-40325f4443b5",
   "title": "Drawing shapes",
   "files": [
    {
     "path": "#tabs",
     "action": "close"
    },
    {
     "path": "#preview: /.guides/p/#preview=/05-drawing/drawing.html&consoleOpen=true&consoleSize=25%25",
     "panel": 0,
     "action": "open"
    }
   ],
   "layout": "2-panels",
   "path": [],
   "type": "html",
   "content-file": ".guides/content/Drawing-shapes-0f89.html",
   "chapter": false,
   "reset": [],
   "teacherOnly": false,
   "closeTerminalSession": true,
   "learningObjectives": ""
  },
  {
   "id": "2ca75684-8468-492f-51db-520ff51db0fc",
   "title": "Colors",
   "files": [],
   "layout": "",
   "path": [],
   "type": "html",
   "content-file": ".guides/content/Colors-2ca7.html",
   "chapter": false,
   "reset": [],
   "teacherOnly": false,
   "closeTerminalSession": true,
   "learningObjectives": ""
  },
  {
   "id": "b6658359-c976-7fc3-60ea-307231e9ece0",
   "title": "Text",
   "files": [],
   "path": [],
   "type": "html",
   "content-file": ".guides/content/Text-b665.html",
   "chapter": false,
   "reset": [],
   "teacherOnly": false,
   "closeTerminalSession": true,
   "learningObjectives": ""
  },
  {
   "id": "a410da03-527b-5632-d2ca-78803621c6ec",
   "title": "Special p5 functions",
   "files": [
    {
     "path": "#tabs",
     "action": "close"
    },
    {
     "path": "05-drawing/drawing.js",
     "panel": 0,
     "action": "open"
    }
   ],
   "layout": "",
   "path": [],
   "type": "html",
   "content-file": ".guides/content/Special-p5-functions-a410.html",
   "chapter": false,
   "reset": [],
   "teacherOnly": false,
   "closeTerminalSession": true,
   "learningObjectives": ""
  },
  {
   "id": "0bf21094-1fb0-b031-f07a-38e4984bd1fa",
   "title": "Animation using the draw() function",
   "files": [
    {
     "path": "#tabs",
     "action": "close"
    },
    {
     "path": "05-drawing/drawing.js",
     "panel": 0,
     "action": "open"
    },
    {
     "path": "#preview: .guides/p/#preview=/05-drawing/drawing.html&consoleOpen",
     "panel": 1,
     "action": "open"
    }
   ],
   "layout": "3-cell",
   "path": [],
   "type": "html",
   "content-file": ".guides/content/Animation-using-the-draw---function-0bf2.html",
   "chapter": false,
   "reset": [],
   "teacherOnly": false,
   "closeTerminalSession": true,
   "learningObjectives": ""
  },
  {
   "id": "3fb98cc7-ba27-164a-299e-9140d1e71d15",
   "title": "Loading and displaying images",
   "files": [
    {
     "path": "05-drawing/drawing.js",
     "panel": 0,
     "action": "open"
    },
    {
     "path": "#preview: .guides/p/#preview=/05-drawing/drawing.html&showConsole",
     "panel": 1,
     "action": "open"
    }
   ],
   "layout": "3-cell-tree",
   "path": [],
   "type": "html",
   "content-file": ".guides/content/Loading-and-displaying-images-3fb9.html",
   "chapter": false,
   "reset": [],
   "teacherOnly": false,
   "closeTerminalSession": true,
   "learningObjectives": ""
  },
  {
   "id": "191f802a-a75c-800e-5649-cee41dc514a0",
   "title": "Anatomy of a p5 script",
   "files": [
    {
     "path": "#tabs",
     "action": "close"
    },
    {
     "path": "05-drawing/drawing.js",
     "panel": 0,
     "action": "open"
    }
   ],
   "layout": "2-panels",
   "path": [],
   "type": "html",
   "content-file": ".guides/content/Anatomy-of-a-p5-script-191f.html",
   "chapter": false,
   "reset": [],
   "teacherOnly": false,
   "closeTerminalSession": true,
   "learningObjectives": ""
  },
  {
   "id": "0c93d5e1-fb19-3a37-4092-175c6354ddba",
   "title": "Variable scope",
   "files": [],
   "path": [],
   "type": "html",
   "content-file": ".guides/content/Variable-scope-0c93.html",
   "chapter": false,
   "reset": [],
   "teacherOnly": false,
   "closeTerminalSession": true,
   "learningObjectives": ""
  },
  {
   "id": "11a0f345-d1cf-6d79-6ca8-3a6d5338381c",
   "title": "Code Challenge: Snowman Sunset",
   "files": [
    {
     "path": "#tabs",
     "action": "close"
    },
    {
     "path": "05-drawing/snowman-sunset.js",
     "panel": 0,
     "action": "open"
    }
   ],
   "layout": "2-panels",
   "path": [],
   "type": "html",
   "content-file": ".guides/content/Code-Challenge--Snowman-Sunset-11a0.html",
   "chapter": false,
   "reset": [],
   "teacherOnly": false,
   "closeTerminalSession": true,
   "learningObjectives": ""
  },
  {
   "id": "e42f85da-086e-4596-1e3c-aeab6663f764",
   "title": "Boolean expressions",
   "files": [
    {
     "path": "#tabs",
     "action": "close"
    },
    {
     "path": "#preview: .guides/p/#consoleOnly",
     "panel": 0,
     "action": "open"
    }
   ],
   "layout": "2-panels",
   "path": [],
   "type": "html",
   "content-file": ".guides/content/Boolean-expressions-e42f.html",
   "chapter": false,
   "reset": [],
   "teacherOnly": false,
   "closeTerminalSession": true,
   "learningObjectives": ""
  },
  {
   "id": "bda12056-936e-f562-2e2f-575a1e843a88",
   "title": "Comparison operators",
   "files": [
    {
     "path": "#tabs",
     "action": "close"
    },
    {
     "path": "#preview: .guides/p/#consoleOnly",
     "panel": 0,
     "action": "open"
    }
   ],
   "layout": "",
   "path": [],
   "type": "html",
   "content-file": ".guides/content/Comparison-operators-bda1.html",
   "chapter": false,
   "reset": [],
   "teacherOnly": false,
   "closeTerminalSession": true,
   "learningObjectives": ""
  },
  {
   "id": "c4d2f923-7a4d-e5f3-dd8b-124350b58510",
   "title": "If statements",
   "files": [
    {
     "path": "#tabs",
     "action": "close"
    },
    {
     "path": "#preview: .guides/p/#consoleOnly",
     "panel": 0,
     "action": "open"
    }
   ],
   "layout": "2-panels",
   "path": [],
   "type": "html",
   "content-file": ".guides/content/If-statements-c4d2.html",
   "chapter": false,
   "reset": [],
   "teacherOnly": false,
   "closeTerminalSession": true,
   "learningObjectives": ""
  },
  {
   "id": "4011f525-3509-0571-a333-0f8f24a7c2da",
   "title": "If statements (practice)",
   "files": [
    {
     "path": "#tabs",
     "action": "close"
    },
    {
     "path": "06-conditions/if-statement.js",
     "panel": 0,
     "action": "open"
    }
   ],
   "layout": "3-cell",
   "path": [],
   "type": "html",
   "content-file": ".guides/content/If-statements--practice--4011.html",
   "chapter": false,
   "reset": [],
   "teacherOnly": false,
   "closeTerminalSession": true,
   "learningObjectives": ""
  },
  {
   "id": "184baaee-7464-9533-6226-595d001eced4",
   "title": "If-else statements",
   "files": [],
   "path": [],
   "type": "html",
   "content-file": ".guides/content/If-else-statements-184b.html",
   "chapter": false,
   "reset": [],
   "teacherOnly": false,
   "closeTerminalSession": true,
   "learningObjectives": ""
  },
  {
   "id": "35c53d47-ef61-28ac-0acb-dd7cc1d5034f",
   "title": "Logical operators",
   "files": [
    {
     "path": "#tabs",
     "action": "close"
    }
   ],
   "layout": "1-panel",
   "path": [],
   "type": "html",
   "content-file": ".guides/content/Logical-operators-35c5.html",
   "chapter": false,
   "reset": [],
   "teacherOnly": false,
   "closeTerminalSession": true,
   "learningObjectives": ""
  },
  {
   "id": "eec6eab2-fd59-591e-f6b0-11b04943df48",
   "title": "Logical operators (practice)",
   "files": [
    {
     "path": "#tabs",
     "action": "close"
    },
    {
     "path": "06-conditions/weather.js",
     "panel": 0,
     "action": "open"
    }
   ],
   "layout": "3-cell",
   "path": [],
   "type": "html",
   "content-file": ".guides/content/Logical-operators--practice--eec6.html",
   "chapter": false,
   "reset": [],
   "teacherOnly": false,
   "closeTerminalSession": true,
   "learningObjectives": ""
  },
  {
   "id": "24f3a213-33f5-1b1b-b7d6-7d502a885c8f",
   "title": "Negation operator",
   "files": [
    {
     "path": "#tabs",
     "action": "close"
    },
    {
     "path": "#preview: .guides/p/#consoleOnly",
     "panel": 0,
     "action": "open"
    }
   ],
   "layout": "2-panels",
   "path": [],
   "type": "html",
   "content-file": ".guides/content/Negation-operator-24f3.html",
   "chapter": false,
   "reset": [],
   "teacherOnly": false,
   "closeTerminalSession": true,
   "learningObjectives": ""
  },
  {
   "id": "992bdb78-ffdf-5d0f-227e-6e133129f113",
   "title": "Code challenge: Pets",
   "files": [
    {
     "path": "#tabs",
     "action": "close"
    },
    {
     "path": "06-conditions/pets.js",
     "panel": 0,
     "action": "open"
    }
   ],
   "layout": "3-cell",
   "path": [],
   "type": "html",
   "content-file": ".guides/content/Code-challenge--Pets-992b.html",
   "chapter": false,
   "reset": [],
   "teacherOnly": false,
   "closeTerminalSession": true,
   "learningObjectives": ""
  },
  {
   "id": "227eb856-a886-e1a6-5342-868574739742",
   "title": "Objects",
   "files": [],
   "path": [],
   "type": "html",
   "content-file": ".guides/content/Objects-227e.html",
   "chapter": false,
   "reset": [],
   "teacherOnly": false,
   "closeTerminalSession": true,
   "learningObjectives": ""
  },
  {
   "id": "db71d767-fcf1-0b08-63a0-10c4b0176ad8",
   "title": "Objects (practice)",
   "files": [],
   "path": [],
   "type": "html",
   "content-file": ".guides/content/Objects--practice--db71.html",
   "chapter": false,
   "reset": [],
   "teacherOnly": false,
   "closeTerminalSession": true,
   "learningObjectives": ""
  },
  {
   "id": "36b7ff98-b3b5-a1ca-0394-ad449151cb93",
   "title": "Adding properties",
   "files": [],
   "path": [],
   "type": "html",
   "content-file": ".guides/content/Adding-properties-36b7.html",
   "chapter": false,
   "reset": [],
   "teacherOnly": false,
   "closeTerminalSession": true,
   "learningObjectives": ""
  },
  {
   "id": "606cf98a-81d6-616e-de67-2bb852d66e5a",
   "title": "Arrays",
   "files": [],
   "path": [],
   "type": "html",
   "content-file": ".guides/content/Arrays-606c.html",
   "chapter": false,
   "reset": [],
   "teacherOnly": false,
   "closeTerminalSession": true,
   "learningObjectives": ""
  },
  {
   "id": "871c3455-1836-3226-5258-baba646d093f",
   "title": "Array Indexes",
   "files": [],
   "path": [],
   "type": "html",
   "content-file": ".guides/content/Array-Indexes-871c.html",
   "chapter": false,
   "reset": [],
   "teacherOnly": false,
   "closeTerminalSession": true,
   "learningObjectives": ""
  },
  {
   "id": "b7d0d9d1-d850-4d99-edd9-ee866f570b69",
   "title": "Adding and removing values at the end",
   "files": [],
   "path": [],
   "type": "html",
   "content-file": ".guides/content/Adding-and-removing-values-at-the-end-b7d0.html",
   "chapter": false,
   "reset": [],
   "teacherOnly": false,
   "closeTerminalSession": true,
   "learningObjectives": ""
  },
  {
   "id": "08455e0d-48f5-aaa9-e673-206f5e339b81",
   "title": "Adding and removing values at the beginning",
   "files": [],
   "path": [],
   "type": "html",
   "content-file": ".guides/content/Adding-and-removing-values-at-the-beginning-0845.html",
   "chapter": false,
   "reset": [],
   "teacherOnly": false,
   "closeTerminalSession": true,
   "learningObjectives": ""
  },
  {
   "id": "b9705102-eeee-64a7-712e-e2556ee22365",
   "title": "More array methods",
   "files": [],
   "path": [],
   "type": "html",
   "content-file": ".guides/content/More-array-methods-b970.html",
   "chapter": false,
   "reset": [],
   "teacherOnly": false,
   "closeTerminalSession": true,
   "learningObjectives": ""
  },
  {
   "id": "9484860e-002b-a00a-e4f9-656d78502c1a",
   "title": "Loops",
   "files": [],
   "path": [],
   "type": "html",
   "content-file": ".guides/content/Loops-9484.html",
   "chapter": false,
   "reset": [],
   "teacherOnly": false,
   "closeTerminalSession": true,
   "learningObjectives": ""
  },
  {
   "id": "2feec3dd-3791-6f4f-912c-0dbb7c2a2dbd",
   "title": "Counting loops",
   "files": [],
   "path": [],
   "type": "html",
   "content-file": ".guides/content/Counting-loops-2fee.html",
   "chapter": false,
   "reset": [],
   "teacherOnly": false,
   "closeTerminalSession": true,
   "learningObjectives": ""
  },
  {
   "id": "3f2e5664-7ef7-a9e9-370d-51811bb028c7",
   "title": "For-of loop",
   "files": [],
   "path": [],
   "type": "html",
   "content-file": ".guides/content/For-of-loop-3f2e.html",
   "chapter": false,
   "reset": [],
   "teacherOnly": false,
   "closeTerminalSession": true,
   "learningObjectives": ""
  },
  {
   "id": "1a8b13e9-dbc5-574a-b779-734c0bae02ab",
   "title": "Coding challenge: Loops",
   "files": [],
   "path": [],
   "type": "html",
   "content-file": ".guides/content/Coding-challenge--Loops-1a8b.html",
   "chapter": false,
   "reset": [],
   "teacherOnly": false,
   "closeTerminalSession": true,
   "learningObjectives": ""
  }
 ],
 "theme": "light",
 "scripts": [],
 "lexikonTopic": "",
 "suppressPageNumbering": true,
 "useSubmitButtons": false,
 "useMarkAsComplete": false,
 "hideMenu": false,
 "allowGuideClose": false,
 "collapsedOnStart": false,
 "hideSectionsToggle": false,
 "hideBackToDashboard": false,
 "protectLayout": false
}